dsm/__init__.py
dsm/app.py
dsm/deps.py
dsm/env.py
dsm/fetcher.py
dsm/init_project.py
dsm/sync.py
dependence_sync-0.2.2.dist-info/LICENSE
dependence_sync-0.2.2.dist-info/METADATA
dependence_sync-0.2.2.dist-info/WHEEL
dependence_sync-0.2.2.dist-info/entry_points.txt
dependence_sync-0.2.2.dist-info/top_level.txt
dependence_sync-0.2.2.dist-info/RECORD
