Metadata-Version: 2.1
Name: dependence-sync
Version: 0.2.2
Summary: Code Dependency Synchronization Management Tool
Home-page: https://gitee.com/zhaosong-lmm_admin/depend-sync
Author: Song Zhao
Author-email: zhaosonggo@163.com
Classifier: Programming Language :: Python :: 3
Classifier: License :: OSI Approved :: Apache Software License
Classifier: Operating System :: OS Independent
License-File: LICENSE
